{
  "date": "20260526",
  "collected_at": "2026-05-26T14:20:33.070429",
  "source": "한국투자증권 KIS API",
  "stocks": [
    {
      "code": "005380",
      "name": "현대차",
      "sector": "자동차",
      "quantity": 33,
      "buy_price": 691439,
      "close": 684000,
      "change": 29000,
      "change_pct": 4.43,
      "volume": 1136248,
      "high": 694000,
      "low": 667000,
      "open": 679000
    },
    {
      "code": "005930",
      "name": "삼성전자",
      "sector": "반도체",
      "quantity": 50,
      "buy_price": 258572,
      "close": 299750,
      "change": 7250,
      "change_pct": 2.48,
      "volume": 16714490,
      "high": 302000,
      "low": 297500,
      "open": 298000
    },
    {
      "code": "006800",
      "name": "미래에셋증권",
      "sector": "금융",
      "quantity": 520,
      "buy_price": 70017,
      "close": 67200,
      "change": -300,
      "change_pct": -0.44,
      "volume": 2017123,
      "high": 70700,
      "low": 66800,
      "open": 70100
    },
    {
      "code": "010120",
      "name": "LS ELECTRIC",
      "sector": "전력/에너지",
      "quantity": 50,
      "buy_price": 185986,
      "close": 283250,
      "change": 2250,
      "change_pct": 0.8,
      "volume": 873785,
      "high": 291000,
      "low": 274000,
      "open": 287000
    },
    {
      "code": "012450",
      "name": "한화에어로스페이스",
      "sector": "방산",
      "quantity": 20,
      "buy_price": 1419433,
      "close": 1254000,
      "change": -7000,
      "change_pct": -0.56,
      "volume": 126837,
      "high": 1275000,
      "low": 1241000,
      "open": 1268000
    },
    {
      "code": "034020",
      "name": "두산에너빌리티",
      "sector": "원전",
      "quantity": 80,
      "buy_price": 103347,
      "close": 112700,
      "change": 1100,
      "change_pct": 0.99,
      "volume": 2681468,
      "high": 115800,
      "low": 111000,
      "open": 114300
    },
    {
      "code": "042660",
      "name": "한화오션",
      "sector": "방산/조선",
      "quantity": 170,
      "buy_price": 132720,
      "close": 132500,
      "change": 10300,
      "change_pct": 8.43,
      "volume": 4238919,
      "high": 139700,
      "low": 123300,
      "open": 126300
    },
    {
      "code": "042700",
      "name": "한미반도체",
      "sector": "반도체",
      "quantity": 50,
      "buy_price": 315200,
      "close": 324500,
      "change": 4000,
      "change_pct": 1.25,
      "volume": 830338,
      "high": 333000,
      "low": 317000,
      "open": 328500
    },
    {
      "code": "052690",
      "name": "한전기술",
      "sector": "전력/에너지",
      "quantity": 110,
      "buy_price": 171918,
      "close": 145900,
      "change": -600,
      "change_pct": -0.41,
      "volume": 98622,
      "high": 149800,
      "low": 144100,
      "open": 149300
    },
    {
      "code": "103590",
      "name": "일진전기",
      "sector": "전력/에너지",
      "quantity": 230,
      "buy_price": 118466,
      "close": 105600,
      "change": -2700,
      "change_pct": -2.49,
      "volume": 391268,
      "high": 111500,
      "low": 104250,
      "open": 111000
    },
    {
      "code": "207940",
      "name": "삼성바이오로직스",
      "sector": "바이오",
      "quantity": 5,
      "buy_price": 1720333,
      "close": 1426000,
      "change": 11000,
      "change_pct": 0.78,
      "volume": 31665,
      "high": 1438000,
      "low": 1416000,
      "open": 1431000
    },
    {
      "code": "272210",
      "name": "한화시스템",
      "sector": "방산",
      "quantity": 200,
      "buy_price": 128823,
      "close": 115400,
      "change": 6000,
      "change_pct": 5.48,
      "volume": 822693,
      "high": 117000,
      "low": 108000,
      "open": 110500
    },
    {
      "code": "277810",
      "name": "레인보우로보틱스",
      "sector": "로봇",
      "quantity": 19,
      "buy_price": 795526,
      "close": 773000,
      "change": 19000,
      "change_pct": 2.52,
      "volume": 85453,
      "high": 798000,
      "low": 766000,
      "open": 782000
    },
    {
      "code": "285130",
      "name": "SK케미칼",
      "sector": "화학/바이오",
      "quantity": 220,
      "buy_price": 57582,
      "close": 46250,
      "change": -50,
      "change_pct": -0.11,
      "volume": 57329,
      "high": 47500,
      "low": 45750,
      "open": 47500
    },
    {
      "code": "388720",
      "name": "유일로보틱스",
      "sector": "로봇",
      "quantity": 140,
      "buy_price": 101843,
      "close": 94050,
      "change": -2250,
      "change_pct": -2.34,
      "volume": 50585,
      "high": 98700,
      "low": 93300,
      "open": 97400
    },
    {
      "code": "454910",
      "name": "두산로보틱스",
      "sector": "로봇",
      "quantity": 244,
      "buy_price": 104392,
      "close": 106900,
      "change": 300,
      "change_pct": 0.28,
      "volume": 804174,
      "high": 110000,
      "low": 106100,
      "open": 109900
    },
    {
      "code": "469150",
      "name": "ACE AI반도체TOP3+",
      "sector": "반도체(ETF)",
      "quantity": 120,
      "buy_price": 46314,
      "close": 77170,
      "change": 3825,
      "change_pct": 5.22,
      "volume": 3005144,
      "high": 77465,
      "low": 74070,
      "open": 74070
    },
    {
      "code": "475150",
      "name": "SK이터닉스",
      "sector": "반도체/소재",
      "quantity": 170,
      "buy_price": 56932,
      "close": 43750,
      "change": -100,
      "change_pct": -0.23,
      "volume": 329996,
      "high": 44700,
      "low": 43400,
      "open": 44550
    }
  ]
}