{
  "date": "20260527",
  "collected_at": "2026-05-27T11:58:53.562207",
  "source": "한국투자증권 KIS API",
  "stocks": [
    {
      "code": "005380",
      "name": "현대차",
      "sector": "자동차",
      "quantity": 33,
      "buy_price": 691439,
      "close": 684000,
      "change": -5000,
      "change_pct": -0.73,
      "volume": 1077155,
      "high": 693000,
      "low": 666000,
      "open": 691000
    },
    {
      "code": "005930",
      "name": "삼성전자",
      "sector": "반도체",
      "quantity": 50,
      "buy_price": 258572,
      "close": 320000,
      "change": 21000,
      "change_pct": 7.02,
      "volume": 17692548,
      "high": 323000,
      "low": 313000,
      "open": 321500
    },
    {
      "code": "006800",
      "name": "미래에셋증권",
      "sector": "금융",
      "quantity": 520,
      "buy_price": 70017,
      "close": 64600,
      "change": -2300,
      "change_pct": -3.44,
      "volume": 1700392,
      "high": 69100,
      "low": 64400,
      "open": 69000
    },
    {
      "code": "010120",
      "name": "LS ELECTRIC",
      "sector": "전력/에너지",
      "quantity": 50,
      "buy_price": 185986,
      "close": 265500,
      "change": -19500,
      "change_pct": -6.84,
      "volume": 721276,
      "high": 282500,
      "low": 265500,
      "open": 282500
    },
    {
      "code": "012450",
      "name": "한화에어로스페이스",
      "sector": "방산",
      "quantity": 20,
      "buy_price": 1419433,
      "close": 1258000,
      "change": 7000,
      "change_pct": 0.56,
      "volume": 150612,
      "high": 1304000,
      "low": 1253000,
      "open": 1262000
    },
    {
      "code": "034020",
      "name": "두산에너빌리티",
      "sector": "원전",
      "quantity": 80,
      "buy_price": 103347,
      "close": 109700,
      "change": -2900,
      "change_pct": -2.58,
      "volume": 1814152,
      "high": 114800,
      "low": 109400,
      "open": 114700
    },
    {
      "code": "042660",
      "name": "한화오션",
      "sector": "방산/조선",
      "quantity": 170,
      "buy_price": 132720,
      "close": 132600,
      "change": -2100,
      "change_pct": -1.56,
      "volume": 1340909,
      "high": 137700,
      "low": 131500,
      "open": 134000
    },
    {
      "code": "042700",
      "name": "한미반도체",
      "sector": "반도체",
      "quantity": 50,
      "buy_price": 315200,
      "close": 320000,
      "change": -9000,
      "change_pct": -2.74,
      "volume": 1318822,
      "high": 354000,
      "low": 317500,
      "open": 350500
    },
    {
      "code": "052690",
      "name": "한전기술",
      "sector": "전력/에너지",
      "quantity": 110,
      "buy_price": 171918,
      "close": 141900,
      "change": -4000,
      "change_pct": -2.74,
      "volume": 57673,
      "high": 147800,
      "low": 141200,
      "open": 147800
    },
    {
      "code": "103590",
      "name": "일진전기",
      "sector": "전력/에너지",
      "quantity": 230,
      "buy_price": 118466,
      "close": 100900,
      "change": -5000,
      "change_pct": -4.72,
      "volume": 256390,
      "high": 107500,
      "low": 100600,
      "open": 106200
    },
    {
      "code": "207940",
      "name": "삼성바이오로직스",
      "sector": "바이오",
      "quantity": 5,
      "buy_price": 1720333,
      "close": 1377000,
      "change": -48000,
      "change_pct": -3.37,
      "volume": 24237,
      "high": 1419000,
      "low": 1375000,
      "open": 1415000
    },
    {
      "code": "272210",
      "name": "한화시스템",
      "sector": "방산",
      "quantity": 200,
      "buy_price": 128823,
      "close": 111000,
      "change": -4000,
      "change_pct": -3.48,
      "volume": 386647,
      "high": 116500,
      "low": 111000,
      "open": 116300
    },
    {
      "code": "277810",
      "name": "레인보우로보틱스",
      "sector": "로봇",
      "quantity": 19,
      "buy_price": 795526,
      "close": 745000,
      "change": -27000,
      "change_pct": -3.5,
      "volume": 80841,
      "high": 769000,
      "low": 741000,
      "open": 768000
    },
    {
      "code": "285130",
      "name": "SK케미칼",
      "sector": "화학/바이오",
      "quantity": 220,
      "buy_price": 57582,
      "close": 44050,
      "change": -2200,
      "change_pct": -4.76,
      "volume": 48280,
      "high": 46800,
      "low": 44000,
      "open": 46600
    },
    {
      "code": "388720",
      "name": "유일로보틱스",
      "sector": "로봇",
      "quantity": 140,
      "buy_price": 101843,
      "close": 90700,
      "change": -3100,
      "change_pct": -3.3,
      "volume": 32160,
      "high": 94000,
      "low": 90400,
      "open": 94000
    },
    {
      "code": "454910",
      "name": "두산로보틱스",
      "sector": "로봇",
      "quantity": 244,
      "buy_price": 104392,
      "close": 104350,
      "change": -2550,
      "change_pct": -2.39,
      "volume": 497296,
      "high": 106900,
      "low": 103000,
      "open": 105700
    },
    {
      "code": "469150",
      "name": "ACE AI반도체TOP3+",
      "sector": "반도체(ETF)",
      "quantity": 120,
      "buy_price": 46314,
      "close": 80700,
      "change": 3785,
      "change_pct": 4.92,
      "volume": 2860104,
      "high": 81180,
      "low": 77850,
      "open": 77860
    },
    {
      "code": "475150",
      "name": "SK이터닉스",
      "sector": "반도체/소재",
      "quantity": 170,
      "buy_price": 56932,
      "close": 40950,
      "change": -2550,
      "change_pct": -5.86,
      "volume": 259450,
      "high": 43700,
      "low": 40500,
      "open": 43700
    }
  ]
}