{
  "date": "20260413",
  "collected_at": "2026-04-13T15:35:18.837451",
  "source": "한국투자증권 KIS API",
  "stocks": [
    {
      "code": "006800",
      "name": "미래에셋증권",
      "sector": "금융",
      "quantity": 30,
      "buy_price": null,
      "close": 65300,
      "change": -1200,
      "change_pct": -1.8,
      "volume": 1563674,
      "high": 66500,
      "low": 64400,
      "open": 64900
    },
    {
      "code": "005930",
      "name": "삼성전자",
      "sector": "반도체",
      "quantity": 6,
      "buy_price": null,
      "close": 201000,
      "change": -5000,
      "change_pct": -2.43,
      "volume": 18836877,
      "high": 203000,
      "low": 198200,
      "open": 198200
    },
    {
      "code": "010120",
      "name": "LS일렉트릭",
      "sector": "에너지/전력",
      "quantity": 17,
      "buy_price": null,
      "close": 179200,
      "change": 21600,
      "change_pct": 13.71,
      "volume": 2570662,
      "high": 188300,
      "low": 171200,
      "open": 171200
    },
    {
      "code": "012450",
      "name": "한화에어로스페이스",
      "sector": "방산",
      "quantity": 16,
      "buy_price": null,
      "close": 1530000,
      "change": 23000,
      "change_pct": 1.53,
      "volume": 165040,
      "high": 1559000,
      "low": 1495000,
      "open": 1526000
    },
    {
      "code": "034020",
      "name": "두산에너빌리티",
      "sector": "에너지/발전",
      "quantity": 700,
      "buy_price": null,
      "close": 99300,
      "change": -900,
      "change_pct": -0.9,
      "volume": 1745686,
      "high": 99300,
      "low": 96700,
      "open": 97900
    },
    {
      "code": "042660",
      "name": "한화오션",
      "sector": "방산/조선",
      "quantity": 100,
      "buy_price": null,
      "close": 120100,
      "change": -3300,
      "change_pct": -2.67,
      "volume": 592086,
      "high": 121600,
      "low": 120000,
      "open": 120700
    },
    {
      "code": "052690",
      "name": "한전기술",
      "sector": "에너지/전력",
      "quantity": 70,
      "buy_price": null,
      "close": 167200,
      "change": 1200,
      "change_pct": 0.72,
      "volume": 161521,
      "high": 168300,
      "low": 160000,
      "open": 162900
    },
    {
      "code": "207940",
      "name": "삼성바이오로직스",
      "sector": "바이오",
      "quantity": 20,
      "buy_price": null,
      "close": 1550000,
      "change": -21000,
      "change_pct": -1.34,
      "volume": 31921,
      "high": 1564000,
      "low": 1542000,
      "open": 1564000
    },
    {
      "code": "272210",
      "name": "한화시스템",
      "sector": "방산",
      "quantity": 170,
      "buy_price": null,
      "close": 131900,
      "change": -1400,
      "change_pct": -1.05,
      "volume": 1071968,
      "high": 138200,
      "low": 130400,
      "open": 138200
    },
    {
      "code": "336260",
      "name": "두산퓨어셀",
      "sector": "에너지/수소",
      "quantity": 90,
      "buy_price": null,
      "close": 37550,
      "change": 1350,
      "change_pct": 3.73,
      "volume": 432116,
      "high": 37800,
      "low": 35000,
      "open": 35600
    },
    {
      "code": "469150",
      "name": "ACE AI반도체TOP3+",
      "sector": "ETF",
      "quantity": 110,
      "buy_price": null,
      "close": 47805,
      "change": -350,
      "change_pct": -0.73,
      "volume": 492910,
      "high": 48125,
      "low": 46825,
      "open": 46925
    }
  ]
}